{
  "m_GameObject": {
    "m_FileID": 0,
    "m_PathID": 0
  },
  "m_Enabled": 1,
  "m_Script": {
    "m_FileID": 0,
    "m_PathID": 3810213884270666000
  },
  "m_Name": "1594",
  "m_id": 1594,
  "m_displayName": "BRAKMAR - Q15 - 11_Porter le slip de Khan Karkass 20 fois",
  "m_availability": 3,
  "m_wip": 0,
  "m_i18nNameId": {
    "a": -960247659,
    "b": 622962948,
    "c": -166269288,
    "d": 1765374158,
    "e": 1086203476
  },
  "m_i18nDescriptionId": {
    "a": 0,
    "b": 0,
    "c": 0,
    "d": 0,
    "e": 0
  },
  "m_i18nDescriptionFinishedId": {
    "a": 0,
    "b": 0,
    "c": 0,
    "d": 0,
    "e": 0
  },
  "values": {
    "type": "AchievementDefinition",
    "id": 1594,
    "subAchievements": [
      479
    ],
    "points": 10,
    "secret": false,
    "achievementType": 0,
    "rewards": [],
    "onSuccess": [],
    "precomputedData": {
      "type": "PrecomputedData",
      "dynamicValueReferences": [],
      "externalDynamicValueReferences": [],
      "hasEffects": false,
      "keywordReferences": [
        {
          "type": 19,
          "id": 455
        },
        {
          "type": 25,
          "id": 797
        },
        {
          "type": 20,
          "id": 159
        }
      ]
    }
  },
  "name": {
    "fr": "Porter le {PropertyEffect:159} 20 fois",
    "en": "Carry the {PropertyEffect:159} 20 times",
    "es": "Ponerte el {PropertyEffect:159} 20 veces",
    "de": "Trage 20x das {PropertyEffect:159}",
    "pt": "Usar a {PropertyEffect:159} 20 vezes"
  }
}