{
  "m_GameObject": {
    "m_FileID": 0,
    "m_PathID": 0
  },
  "m_Enabled": 1,
  "m_Script": {
    "m_FileID": 0,
    "m_PathID": 3810213884270666467
  },
  "m_Name": "1923",
  "m_id": 1923,
  "m_displayName": "BONTA - Q05 - 18_Remporter un combat sans déclencher l'attaque d'un Rat Klure",
  "m_availability": 3,
  "m_wip": 0,
  "m_i18nNameId": {
    "a": -707614299,
    "b": 739590020,
    "c": -1500926248,
    "d": 613706802,
    "e": -173422034
  },
  "m_i18nDescriptionId": {
    "a": 0,
    "b": 0,
    "c": 0,
    "d": 0,
    "e": 0
  },
  "m_i18nDescriptionFinishedId": {
    "a": 0,
    "b": 0,
    "c": 0,
    "d": 0,
    "e": 0
  },
  "values": {
    "type": "AchievementDefinition",
    "id": 1923,
    "subAchievements": [
      230
    ],
    "points": 15,
    "secret": false,
    "achievementType": 0,
    "rewards": [],
    "onSuccess": [],
    "precomputedData": {
      "type": "PrecomputedData",
      "dynamicValueReferences": [],
      "externalDynamicValueReferences": [],
      "hasEffects": false,
      "keywordReferences": [
        {
          "type": 4,
          "id": 456
        }
      ]
    }
  },
  "name": {
    "fr": "Remporter un combat sans déclencher l'attaque d'un {Summoning:456}",
    "en": "Win a fight without triggering an attack by a {Summoning:456}",
    "es": "Ganar un combate sin activar el ataque de una {Summoning:456}",
    "de": "Gewinne einen Kampf, ohne den Angriff von {Summoning:456} auszulösen",
    "pt": "Vencer um combate sem acionar o ataque de um {Summoning:456}"
  }
}