{
  "m_GameObject": {
    "m_FileID": 0,
    "m_PathID": 0
  },
  "m_Enabled": 1,
  "m_Script": {
    "m_FileID": 0,
    "m_PathID": 3810213884270666000
  },
  "m_Name": "1997",
  "m_id": 1997,
  "m_displayName": "AMAKNA - Q06 - 10_Completer le Chapitre I en Diamant",
  "m_availability": 3,
  "m_wip": 0,
  "m_i18nNameId": {
    "a": -1073308982,
    "b": -447083836,
    "c": -128309637,
    "d": 1258696681,
    "e": 1896076340
  },
  "m_i18nDescriptionId": {
    "a": 0,
    "b": 0,
    "c": 0,
    "d": 0,
    "e": 0
  },
  "m_i18nDescriptionFinishedId": {
    "a": 0,
    "b": 0,
    "c": 0,
    "d": 0,
    "e": 0
  },
  "values": {
    "type": "AchievementDefinition",
    "id": 1997,
    "subAchievements": [
      2386
    ],
    "points": 10,
    "secret": false,
    "achievementType": 0,
    "rewards": [],
    "onSuccess": [],
    "precomputedData": {
      "type": "PrecomputedData",
      "dynamicValueReferences": [],
      "externalDynamicValueReferences": [],
      "hasEffects": false,
      "keywordReferences": []
    }
  },
  "name": {
    "fr": "Compléter le Chapitre I en Diamant",
    "en": "Complete Chapter I in Diamond",
    "es": "Completar el capítulo I en Diamante",
    "de": "Schließ Kapitel I in Diamant ab",
    "pt": "Completar o Capítulo I com Diamante"
  }
}