{
  "m_GameObject": {
    "m_FileID": 0,
    "m_PathID": 0
  },
  "m_Enabled": 1,
  "m_Script": {
    "m_FileID": 0,
    "m_PathID": 3810213884270666467
  },
  "m_Name": "2110",
  "m_id": 2110,
  "m_displayName": "ALBUERA - Q01 - 02_Completer le Donjon avec Lance Dur sur le terrain",
  "m_availability": 3,
  "m_wip": 0,
  "m_i18nNameId": {
    "a": -1047639903,
    "b": 400761940,
    "c": -202102312,
    "d": -461788271,
    "e": -1857172976
  },
  "values": {
    "type": "AchievementDefinition",
    "id": 2110,
    "subAchievements": [
      3298
    ],
    "_toRemove": 0,
    "points": 10,
    "secret": false,
    "achievementType": 0,
    "rewards": [],
    "onSuccess": [],
    "precomputedData": {
      "type": "PrecomputedData",
      "dynamicValueReferences": [],
      "externalDynamicValueReferences": [],
      "hasEffects": false,
      "keywordReferences": [
        {
          "type": 22,
          "id": 208
        },
        {
          "type": 20,
          "id": 173
        },
        {
          "type": 20,
          "id": 20
        },
        {
          "type": 5,
          "id": 554
        },
        {
          "type": 4,
          "id": 1394
        }
      ]
    }
  },
  "name": {
    "fr": "Remporter un combat contre {Summoning:1394} en ayant {Companion:554} sur le terrain",
    "en": "Win a fight against {Summoning:1394} with {Companion:554} on the field",
    "es": "Ganar un combate contra {Summoning:1394} teniendo a {Companion:554} en el terreno",
    "de": "Gewinne einen Kampf gegen {Summoning:1394}, während sich {Companion:554} auf dem Spielfeld befindet",
    "pt": "Vencer um combate contra {Summoning:1394} com {Companion:554} no campo de batalha"
  }
}