{
  "m_GameObject": {
    "m_FileID": 0,
    "m_PathID": 0
  },
  "m_Enabled": 1,
  "m_Script": {
    "m_FileID": 0,
    "m_PathID": 3810213884270666000
  },
  "m_Name": "329",
  "m_id": 329,
  "m_displayName": "BRAKMAR - Q03 - 19_Subir 20 attaques ASSOIFFE en un seul Combat  ",
  "m_availability": 3,
  "m_i18nNameId": {
    "a": 638921539,
    "b": 2102788708,
    "c": 1204587371,
    "d": -1444875470,
    "e": 1721030390
  },
  "m_i18nDescriptionId": {
    "a": 0,
    "b": 0,
    "c": 0,
    "d": 0,
    "e": 0
  },
  "m_i18nDescriptionFinishedId": {
    "a": 0,
    "b": 0,
    "c": 0,
    "d": 0,
    "e": 0
  },
  "values": {
    "type": "AchievementDefinition",
    "id": 329,
    "subAchievements": [
      280
    ],
    "points": 15,
    "secret": false,
    "achievementType": 0,
    "rewards": [],
    "onSuccess": [],
    "precomputedData": {
      "type": "PrecomputedData",
      "dynamicValueReferences": [],
      "externalDynamicValueReferences": [],
      "hasEffects": false,
      "keywordReferences": [
        "DRAIN",
        {
          "type": 20,
          "id": 82
        }
      ]
    }
  },
  "name": {
    "fr": "Subir 20 <b>ATTAQUES</b> {PropertyEffect:82[ASSOIFFÉES]} en un seul combat  ",
    "en": "",
    "es": "",
    "de": "",
    "pt": ""
  },
  "description": {
    "fr": "",
    "en": "",
    "es": "",
    "de": "",
    "pt": ""
  },
  "descriptionFinished": {
    "fr": "",
    "en": "",
    "es": "",
    "de": "",
    "pt": ""
  }
}