{
  "m_GameObject": {
    "m_FileID": 0,
    "m_PathID": 0
  },
  "m_Enabled": 1,
  "m_Script": {
    "m_FileID": 0,
    "m_PathID": 3810213884270666000
  },
  "m_Name": "495",
  "m_id": 495,
  "m_displayName": "BWORK - DUNGEON - 57_Remporter le combat en achevant Bworky Pro Graisse dun seul coup",
  "m_availability": 3,
  "m_wip": 0,
  "m_i18nNameId": {
    "a": 1175963823,
    "b": -1885173404,
    "c": 394067368,
    "d": 568446272,
    "e": -88004273
  },
  "m_i18nDescriptionId": {
    "a": 0,
    "b": 0,
    "c": 0,
    "d": 0,
    "e": 0
  },
  "m_i18nDescriptionFinishedId": {
    "a": 0,
    "b": 0,
    "c": 0,
    "d": 0,
    "e": 0
  },
  "values": {
    "type": "AchievementDefinition",
    "id": 495,
    "subAchievements": [
      679
    ],
    "points": 5,
    "secret": false,
    "achievementType": 0,
    "rewards": [],
    "onSuccess": [],
    "precomputedData": {
      "type": "PrecomputedData",
      "dynamicValueReferences": [],
      "externalDynamicValueReferences": [],
      "hasEffects": false,
      "keywordReferences": [
        {
          "type": 1,
          "id": 2968
        }
      ]
    }
  },
  "name": {
    "fr": "Remporter le combat en achevant {Skin:2968} d'un seul coup",
    "en": "Win the fight, finishing off {Skin:2968} with a single blow",
    "es": "Ganar el combate acabando con {Skin:2968} de un solo golpe",
    "de": "Gewinne den Kampf, indem du {Skin:2968} mit nur einem Treffer besiegst",
    "pt": "Vencer o combate derrotando {Skin:2968} com um só golpe"
  }
}