{
  "m_GameObject": {
    "m_FileID": 0,
    "m_PathID": 0
  },
  "m_Enabled": 1,
  "m_Script": {
    "m_FileID": 0,
    "m_PathID": 5531694572057177000
  },
  "m_Name": "1166",
  "m_id": 1166,
  "m_displayName": "Iop - Kasai Passive",
  "m_availability": 3,
  "m_wip": 0,
  "values": {
    "type": "FxDefinition",
    "id": 1166,
    "spellEffectData": [
      {
        "type": "SpellEffectInstantiationData",
        "spellEffect": "f3acc1020a101e3449fc2054cd6cf013",
        "originTarget": {
          "type": "FirstCastTargetSelector"
        },
        "orientation": null,
        "delay": null
      }
    ]
  }
}