{
  "m_GameObject": {
    "m_FileID": 0,
    "m_PathID": 0
  },
  "m_Enabled": 1,
  "m_Script": {
    "m_FileID": 0,
    "m_PathID": -6887862329953422503
  },
  "m_Name": "235",
  "m_id": 235,
  "m_displayName": "STORY MODE - Attaque Proliferation",
  "m_availability": 3,
  "m_wip": 0,
  "values": {
    "type": "FxDefinition",
    "id": 235,
    "spellEffectData": [
      {
        "type": "SpellEffectInstantiationData",
        "spellEffect": "57032171ddc57104ab2e35de33ded5f8",
        "originTarget": {
          "type": "FirstCastTargetSelector"
        },
        "orientation": null,
        "delay": null
      }
    ]
  }
}