{
  "m_GameObject": {
    "m_FileID": 0,
    "m_PathID": 0
  },
  "m_Enabled": 1,
  "m_Script": {
    "m_FileID": 0,
    "m_PathID": -19042880005626584
  },
  "m_Name": "2",
  "m_id": 2,
  "m_displayName": "Placeholder FloorMechanism",
  "m_availability": 3,
  "m_wip": 0,
  "m_i18nNameId": {
    "a": -524408809,
    "b": -1157828812,
    "c": -1866084678,
    "d": -90393388,
    "e": -1790913172
  },
  "m_i18nEffectDescriptionId": {
    "a": -524408809,
    "b": -1157828812,
    "c": -1866084678,
    "d": -90393388,
    "e": 2062003888
  },
  "animatedCharacterDataReference": {
    "assetGuid": "12d152314ee2a0346bb721dff718e932"
  },
  "animatedCharacterUIPreviewReference": {
    "assetGuid": ""
  },
  "animatedCharacterUIPreviewScale": 1,
  "animatedIllustrationReference": {
    "assetGuid": ""
  },
  "illustrationReference": {
    "assetGuid": ""
  },
  "slotIllustrationReference": {
    "assetGuid": ""
  },
  "localizedBadgeIllustrationReference": {
    "assetGuid": ""
  },
  "npcTalkFightVictoryAssetReference": {
    "assetGuid": ""
  },
  "npcTalkFightDefeatAssetReference": {
    "assetGuid": ""
  },
  "npcTalkQuestTalkAssetReference": {
    "assetGuid": ""
  },
  "npcTalkQuestSuccessAssetReference": {
    "assetGuid": ""
  },
  "questSmallIllustrationAssetReference": {
    "assetGuid": ""
  },
  "voiceLine": {
    "m_eventGuid": "",
    "m_parameterIds": [],
    "m_parameterValues": []
  },
  "values": {
    "type": "CharacterSkinDefinition",
    "id": 2,
    "rarity": 0,
    "merchantCosts": [],
    "purchaseConditionalAvailability": {
      "type": "Available"
    },
    "precomputedData": {
      "type": "PrecomputedData",
      "dynamicValueReferences": [],
      "externalDynamicValueReferences": [],
      "hasEffects": false,
      "keywordReferences": []
    },
    "characterSkinType": 0,
    "gender": 1,
    "defaultEmotes": [],
    "faction": null,
    "chromaParentId": null
  },
  "name": {
    "fr": "Placeholder",
    "en": "Placeholder",
    "es": "Placeholder",
    "de": "Platzhalter",
    "pt": "Placeholder"
  }
}