{
  "m_GameObject": {
    "m_FileID": 0,
    "m_PathID": 0
  },
  "m_Enabled": 1,
  "m_Script": {
    "m_FileID": 0,
    "m_PathID": -8350537487672278491
  },
  "m_Name": "40",
  "m_id": 40,
  "m_displayName": "PET - RAT - Ramoilles",
  "m_availability": 3,
  "m_wip": 0,
  "m_i18nNameId": {
    "a": 518608320,
    "b": -1846206012,
    "c": 1564619450,
    "d": -1617062675,
    "e": -655616071
  },
  "m_i18nEffectDescriptionId": {
    "a": 0,
    "b": 0,
    "c": 0,
    "d": 0,
    "e": 0
  },
  "animatedCharacterDataReference": {
    "assetGuid": "627a9bbb957b1494eadaaca8acd3c524"
  },
  "animatedCharacterUIPreviewReference": {
    "assetGuid": "91295821bcc2fa8468f091b4de33167f"
  },
  "animatedCharacterUIPreviewScale": 0.8999999761581421,
  "animatedIllustrationReference": {
    "assetGuid": ""
  },
  "illustrationReference": {
    "assetGuid": ""
  },
  "slotIllustrationReference": {
    "assetGuid": ""
  },
  "localizedBadgeIllustrationReference": {
    "assetGuid": ""
  },
  "npcTalkFightVictoryAssetReference": {
    "assetGuid": ""
  },
  "npcTalkFightDefeatAssetReference": {
    "assetGuid": ""
  },
  "npcTalkQuestTalkAssetReference": {
    "assetGuid": ""
  },
  "npcTalkQuestSuccessAssetReference": {
    "assetGuid": ""
  },
  "questSmallIllustrationAssetReference": {
    "assetGuid": ""
  },
  "voiceLine": {
    "m_eventGuid": "",
    "m_parameterIds": [],
    "m_parameterValues": []
  },
  "values": {
    "type": "CharacterSkinDefinition",
    "id": 40,
    "rarity": 0,
    "merchantCosts": [],
    "purchaseConditionalAvailability": {
      "type": "Available"
    },
    "precomputedData": {
      "type": "PrecomputedData",
      "dynamicValueReferences": [],
      "externalDynamicValueReferences": [],
      "hasEffects": false,
      "keywordReferences": []
    },
    "characterSkinType": 10,
    "gender": 1,
    "defaultEmotes": [],
    "faction": null,
    "chromaParentId": null
  },
  "name": {
    "fr": "Ramoilles",
    "en": "Ratilton",
    "es": "Raquesón",
    "de": "Ratzfatz",
    "pt": "Ratonzola"
  }
}