{
  "m_GameObject": {
    "m_FileID": 0,
    "m_PathID": 0
  },
  "m_Enabled": 1,
  "m_Script": {
    "m_FileID": 0,
    "m_PathID": -19042880005626584
  },
  "m_Name": "7876",
  "m_id": 7876,
  "m_displayName": "MECHANISM - BRAKMAR - Table de Dissection 3",
  "m_availability": 3,
  "m_i18nNameId": {
    "a": 915134917,
    "b": -1275044012,
    "c": -498304760,
    "d": -1056557040,
    "e": 1763227468
  },
  "m_i18nEffectDescriptionId": {
    "a": 0,
    "b": 0,
    "c": 0,
    "d": 0,
    "e": 0
  },
  "animatedCharacterDataReference": {
    "assetGuid": "7c49100e81dd4b04f9092a570b0d5cc3"
  },
  "animatedCharacterUIPreviewReference": {
    "assetGuid": ""
  },
  "animatedCharacterUIPreviewScale": 1,
  "animatedIllustrationReference": {
    "assetGuid": ""
  },
  "illustrationReference": {
    "assetGuid": "f6f45420ef979ae45b2fe01c6072c950"
  },
  "slotIllustrationReference": {
    "assetGuid": ""
  },
  "npcTalkFightVictoryAssetReference": {
    "assetGuid": ""
  },
  "npcTalkFightDefeatAssetReference": {
    "assetGuid": ""
  },
  "npcTalkQuestTalkAssetReference": {
    "assetGuid": ""
  },
  "npcTalkQuestSuccessAssetReference": {
    "assetGuid": ""
  },
  "questSmallIllustrationAssetReference": {
    "assetGuid": ""
  },
  "voiceLine": {
    "m_eventGuid": "",
    "m_parameterIds": [],
    "m_parameterValues": []
  },
  "values": {
    "type": "CharacterSkinDefinition",
    "id": 7876,
    "rarity": 0,
    "merchantCosts": [],
    "premiumItem": false,
    "precomputedData": {
      "type": "PrecomputedData",
      "dynamicValueReferences": [],
      "externalDynamicValueReferences": [],
      "hasEffects": false,
      "keywordReferences": []
    },
    "characterSkinType": 3,
    "gender": 1,
    "defaultEmotes": [],
    "faction": null
  },
  "name": {
    "fr": "Table de Dissection 3",
    "en": "Dissection Table 3",
    "es": "Mesa de Disección 3",
    "de": "Seziertisch 3",
    "pt": "Tabela de Dissecação 3"
  }
}