{
  "m_GameObject": {
    "m_FileID": 0,
    "m_PathID": 0
  },
  "m_Enabled": 1,
  "m_Script": {
    "m_FileID": 0,
    "m_PathID": -19042880005626584
  },
  "m_Name": "8901",
  "m_id": 8901,
  "m_displayName": "WEAPON - OSAMODAS - Berger Prespic M - Skin 01",
  "m_availability": 3,
  "m_wip": 1,
  "m_i18nNameId": {
    "a": 665086118,
    "b": -1535518988,
    "c": 1991331176,
    "d": -1700679757,
    "e": 965047696
  },
  "m_i18nEffectDescriptionId": {
    "a": 0,
    "b": 0,
    "c": 0,
    "d": 0,
    "e": 0
  },
  "animatedCharacterDataReference": {
    "assetGuid": "afd1fe5960e6c0a4e8118a70589a0efd"
  },
  "animatedCharacterUIPreviewReference": {
    "assetGuid": "dcdc63a1fefdfa04a898110cb84f1b8a"
  },
  "animatedCharacterUIPreviewScale": 1,
  "animatedIllustrationReference": {
    "assetGuid": "1decc6bcaf7ca014bb5c0d3c7570cd84"
  },
  "illustrationReference": {
    "assetGuid": "793dbdcdf2794344e969deda772b42dc"
  },
  "slotIllustrationReference": {
    "assetGuid": ""
  },
  "localizedBadgeIllustrationReference": {
    "assetGuid": ""
  },
  "npcTalkFightVictoryAssetReference": {
    "assetGuid": ""
  },
  "npcTalkFightDefeatAssetReference": {
    "assetGuid": ""
  },
  "npcTalkQuestTalkAssetReference": {
    "assetGuid": ""
  },
  "npcTalkQuestSuccessAssetReference": {
    "assetGuid": ""
  },
  "questSmallIllustrationAssetReference": {
    "assetGuid": ""
  },
  "voiceLine": {
    "m_eventGuid": "",
    "m_parameterIds": [],
    "m_parameterValues": []
  },
  "values": {
    "type": "CharacterSkinDefinition",
    "id": 8901,
    "rarity": 0,
    "merchantCosts": [],
    "purchaseConditionalAvailability": {
      "type": "Available"
    },
    "precomputedData": {
      "type": "PrecomputedData",
      "dynamicValueReferences": [],
      "externalDynamicValueReferences": [],
      "hasEffects": false,
      "keywordReferences": []
    },
    "characterSkinType": 7,
    "gender": 1,
    "defaultEmotes": [
      390,
      658,
      252
    ],
    "faction": null,
    "chromaParentId": null
  },
  "name": {
    "fr": "Dompteur d'Épines"
  }
}