{
  "m_GameObject": {
    "m_FileID": 0,
    "m_PathID": 0
  },
  "m_Enabled": 1,
  "m_Script": {
    "m_FileID": 0,
    "m_PathID": 7339724952593503880
  },
  "m_Name": "253",
  "m_id": 253,
  "m_displayName": "SEASON - MOUETTE - Naufrage",
  "m_availability": 3,
  "m_wip": 1,
  "m_i18nNameId": {
    "a": -1414249383,
    "b": -72401980,
    "c": 1499156890,
    "d": -1102252029,
    "e": 872167919
  },
  "m_i18nDescriptionId": {
    "a": -1414249383,
    "b": -72401980,
    "c": 1499156890,
    "d": -1102252029,
    "e": -62497143
  },
  "m_i18nGameplayDescriptionId": {
    "a": 0,
    "b": 0,
    "c": 0,
    "d": 0,
    "e": 0
  },
  "m_i18nSimpleNameId": {
    "a": 0,
    "b": 0,
    "c": 0,
    "d": 0,
    "e": 0
  },
  "m_i18nSimpleDescriptionId": {
    "a": 0,
    "b": 0,
    "c": 0,
    "d": 0,
    "e": 0
  },
  "m_weaponIllustrationReference": {
    "assetGuid": "c788329854ecce146a1e46d1cc2f9ac4"
  },
  "m_weaponUnlockedIllustrationReference": {
    "assetGuid": ""
  },
  "values": {
    "type": "WeaponDefinition",
    "id": 253,
    "characterSpecificSkins": {
      "type": "CharacterSpecificSkins",
      "defaultSkinId": 1677,
      "skinIds": [
        1677
      ]
    },
    "precomputedData": {
      "type": "PrecomputedData",
      "dynamicValueReferences": [],
      "externalDynamicValueReferences": [],
      "hasEffects": false,
      "keywordReferences": []
    },
    "families": [
      0
    ],
    "baseProperties": [],
    "life": {
      "type": "ConstIntegerValue",
      "referenceId": "",
      "value": 2000
    },
    "movementPoints": {
      "type": "ConstIntegerValue",
      "referenceId": "",
      "value": 4
    },
    "actionValue": {
      "type": "ConstIntegerValue",
      "referenceId": "",
      "value": 100
    },
    "riposte": null,
    "actionCriticalChance": null,
    "actionCriticalBonus": null,
    "customActionTarget": null,
    "actionType": 1,
    "actionRange": null,
    "lifeScale": null,
    "attackScale": null,
    "merchantCosts": [],
    "purchaseConditionalAvailability": {
      "type": "Hidden"
    },
    "unlockableSkillIds": [],
    "difficultyHint": 1,
    "defaultSkinIdMale": 1677,
    "defaultSkinIdFemale": 1677,
    "god": 0,
    "conditionalAvailability": {
      "type": "Hidden"
    },
    "playerActionPoints": {
      "type": "ConstIntegerValue",
      "referenceId": "",
      "value": 12
    },
    "resurrectAs": null,
    "hasPresentationVideo": false,
    "unlockableSpells": [],
    "presetSpellIndexForTutorialCompanionElementReference": 2,
    "presetSpellIds": []
  },
  "name": {
    "fr": "Naufragé",
    "en": "Castaway",
    "es": "Naufragado",
    "de": "Schiffbrüchiger",
    "pt": "Náufrago"
  },
  "description": {
    "fr": "Quelle arme choisir\\_?",
    "en": "Which weapon?",
    "es": "¿Qué arma elegir?",
    "de": "Welche Waffe soll es sein?",
    "pt": "Qual arma escolher?"
  }
}