{
  "m_GameObject": {
    "m_FileID": 0,
    "m_PathID": 0
  },
  "m_Enabled": 1,
  "m_Script": {
    "m_FileID": 0,
    "m_PathID": -7716175787133228619
  },
  "m_Name": "4298",
  "m_id": 4298,
  "m_displayName": "Season 23_Kerubim - Semaine 2 - 02_Declencher 6 attaques en un seul tour",
  "m_availability": 3,
  "m_wip": 1,
  "values": {
    "type": "SubAchievementDefinition",
    "id": 4298,
    "parentDataId": {
      "typeEnum": 45,
      "value": 366
    },
    "completionThreshold": 1,
    "parameters": {
      "type": "SubAchievementFightData"
    }
  }
}