{
  "m_GameObject": {
    "m_FileID": 0,
    "m_PathID": 0
  },
  "m_Enabled": 1,
  "m_Script": {
    "m_FileID": 0,
    "m_PathID": -7716175787133228619
  },
  "m_Name": "624",
  "m_id": 624,
  "m_displayName": "BONTA - Q16 - 08_Chapitre 10 Diamant",
  "m_availability": 3,
  "m_wip": 0,
  "values": {
    "type": "SubAchievementDefinition",
    "id": 624,
    "parentDataId": {
      "typeEnum": 28,
      "value": 814
    },
    "completionThreshold": 1,
    "parameters": {
      "type": "SubAchievementQuestData",
      "questId": 129,
      "chapter": {
        "type": "ChapterOrdinalValue",
        "chapterOrdinalInRank": 10,
        "rank": 4
      }
    }
  }
}