{
  "m_GameObject": {
    "m_FileID": 0,
    "m_PathID": 0
  },
  "m_Enabled": 1,
  "m_Script": {
    "m_FileID": 0,
    "m_PathID": -5399370413391876000
  },
  "m_Name": "66",
  "m_id": 66,
  "m_displayName": "DQ - SECRET ZONE - CHUCHOTEUR - 2_Couloirs du Château",
  "m_availability": 3,
  "m_wip": 0,
  "m_iosInfoSerialized": "[{\"objectName\":0,\"subZoneId\":0,\"state\":2,\"interactionIndex\":0,\"additionalInfo\":{\"subZoneId\":1,\"type\":3}},{\"objectName\":0,\"subZoneId\":1,\"state\":2,\"interactionIndex\":0,\"additionalInfo\":{\"subZoneId\":2,\"type\":3}}]",
  "m_subZoneInfos": [
    {
      "subZoneId": 0,
      "subZoneNameTextKey": {
        "a": 537381533,
        "b": -467773820,
        "c": 265205513,
        "d": 2110872570,
        "e": 1612415233
      }
    },
    {
      "subZoneId": 1,
      "subZoneNameTextKey": {
        "a": 537381533,
        "b": -467773820,
        "c": 265205513,
        "d": 2110872570,
        "e": 1466811733
      }
    },
    {
      "subZoneId": 2,
      "subZoneNameTextKey": {
        "a": 537381533,
        "b": -467773820,
        "c": 265205513,
        "d": 2110872570,
        "e": -984242773
      }
    }
  ],
  "m_i18nNameId": {
    "a": 537381533,
    "b": -467773820,
    "c": 265205513,
    "d": 2110872570,
    "e": -404707127
  },
  "values": {
    "type": "DungeonZoneDefinition",
    "id": 66,
    "zoneType": 3,
    "customResourcesToDisplay": []
  },
  "name": {
    "fr": "",
    "en": "",
    "es": "",
    "de": "",
    "pt": ""
  }
}