{
  "m_GameObject": {
    "m_FileID": 0,
    "m_PathID": 0
  },
  "m_Enabled": 1,
  "m_Script": {
    "m_FileID": 0,
    "m_PathID": -6871528616786842945
  },
  "m_Name": "154",
  "m_id": 154,
  "m_displayName": "EQUIPMENT - BRASSARD - Turien 1",
  "m_availability": 3,
  "m_wip": 0,
  "m_i18nNameId": {
    "a": -708379428,
    "b": -1655547452,
    "c": -229689189,
    "d": -1909761222,
    "e": -250843310
  },
  "m_i18nDescriptionId": {
    "a": -708379428,
    "b": -1655547452,
    "c": -229689189,
    "d": -1909761222,
    "e": -1612379936
  },
  "m_skillIconReference": {
    "assetGuid": "cd1845e0374830c4e8cf8b6f4439191e"
  },
  "values": {
    "type": "SkillDefinition",
    "id": 154,
    "skillTier": 3,
    "skillUsageType": 2,
    "hideDescriptionInTooltip": false,
    "passiveModifiers": [],
    "nonFightSkillEffects": [],
    "precomputedData": {
      "type": "PrecomputedData",
      "dynamicValueReferences": [],
      "externalDynamicValueReferences": [],
      "hasEffects": false,
      "keywordReferences": [
        "PEAT",
        "CRITICAL"
      ]
    }
  },
  "name": {
    "fr": "{%UPGRADED_SKILL}",
    "en": "{%UPGRADED_SKILL}",
    "es": "{%UPGRADED_SKILL}",
    "de": "{%UPGRADED_SKILL}",
    "pt": "{%UPGRADED_SKILL}"
  },
  "description": {
    "fr": "{#CRITICAL}\\_: Déclenche {#PEAT} une seconde fois.",
    "en": "{#CRITICAL}: Triggers {#PEAT} a second time.",
    "es": "{#CRITICAL}: Activa {#PEAT} una segunda vez.",
    "de": "{#CRITICAL}: Löst ein zweites Mal {#PEAT} aus.",
    "pt": "{#CRITICAL}: Aciona {#PEAT} uma segunda vez."
  }
}