{
  "m_GameObject": {
    "m_FileID": 0,
    "m_PathID": 0
  },
  "m_Enabled": 1,
  "m_Script": {
    "m_FileID": 0,
    "m_PathID": -6871528616786842945
  },
  "m_Name": "314",
  "m_id": 314,
  "m_displayName": "WEAPON - CRA - BUNELAME - Maître Bunelame",
  "m_availability": 3,
  "m_wip": 0,
  "m_i18nNameId": {
    "a": -2144895917,
    "b": -1928563692,
    "c": 1267872395,
    "d": -608164679,
    "e": -1519099946
  },
  "m_i18nDescriptionId": {
    "a": -2144895917,
    "b": -1928563692,
    "c": 1267872395,
    "d": -608164679,
    "e": 645401505
  },
  "m_skillIconReference": {
    "assetGuid": "58608d959339ca34fa6656526ca0215b"
  },
  "values": {
    "type": "SkillDefinition",
    "id": 314,
    "skillTier": 1,
    "skillUsageType": 5,
    "hideDescriptionInTooltip": false,
    "passiveModifiers": [],
    "precomputedData": {
      "type": "PrecomputedData",
      "dynamicValueReferences": [
        {
          "type": "ConstIntegerValue",
          "referenceId": "va",
          "value": 3
        },
        {
          "type": "ConstIntegerValue",
          "referenceId": "pc",
          "value": 20
        },
        {
          "type": "ConstIntegerValue",
          "referenceId": "per",
          "value": 25
        }
      ],
      "externalDynamicValueReferences": [],
      "hasEffects": true,
      "keywordReferences": []
    }
  },
  "name": {
    "fr": "Maître Bunelame",
    "en": "Buneblade Master",
    "es": "Maestro Bunehoja",
    "de": "Bunklingen-Beherrschung",
    "pt": "Mestre Bumelâmina"
  },
  "description": {
    "fr": "Lorsque vous jouez un sort coûtant {PAvalue:va} ou moins\\_: {ATvalue:per,percent,+} à votre héros et {value:pc,percent,+} {%All_ELEMENTS} pour le tour.",
    "en": "When you play a spell costing {PAvalue:va} or less: {ATvalue:per,percent,+} to your hero and {value:pc,percent,+} {%All_ELEMENTS} for the turn.",
    "es": "Cuando lanzas un hechizo que cuesta {PAvalue:va} o menos: {ATvalue:per,percent,+} a tu héroe y {value:pc,percent,+} {%All_ELEMENTS} durante el turno.",
    "de": "Wenn du einen Zauber wirkst, der {PAvalue:va} oder weniger kostet: {ATvalue:per,percent,+} für deinen Helden und {value:pc,percent,+}{%All_ELEMENTS} für die Runde.",
    "pt": "Quando você lança um feitiço que custa {PAvalue:va} ou menos: {ATvalue:per,percent,+} ao seu herói e {value:pc,percent,+} {%All_ELEMENTS} durante o turno."
  }
}