{
  "m_GameObject": {
    "m_FileID": 0,
    "m_PathID": 0
  },
  "m_Enabled": 1,
  "m_Script": {
    "m_FileID": 0,
    "m_PathID": -6962076302617524000
  },
  "m_Name": "587",
  "m_id": 587,
  "m_displayName": "SPELL - IOP - ARME - Glaive Stalaktoss - AIR - Trouble 1",
  "m_availability": 3,
  "m_i18nNameId": {
    "a": -1497093313,
    "b": -662427964,
    "c": 1656037098,
    "d": 296221128,
    "e": -1012083917
  },
  "m_i18nDescriptionId": {
    "a": -1497093313,
    "b": -662427964,
    "c": 1656037098,
    "d": 296221128,
    "e": -554690379
  },
  "m_skillIconReference": {
    "assetGuid": "a632daece8b982f4da75889d298082d7"
  },
  "values": {
    "type": "SkillDefinition",
    "id": 587,
    "skillUsageType": 0,
    "hideDescriptionInTooltip": true,
    "passiveModifiers": [],
    "nonFightSkillEffects": [],
    "precomputedData": {
      "type": "PrecomputedData",
      "dynamicValueReferences": [],
      "externalDynamicValueReferences": [
        "Spell.119042.d1"
      ],
      "hasEffects": false,
      "keywordReferences": [
        "PUSH"
      ]
    }
  },
  "name": {
    "fr": "{%UPGRADED_SKILL}",
    "en": "{%UPGRADED_SKILL}",
    "es": "{%UPGRADED_SKILL}",
    "de": "{%UPGRADED_SKILL}",
    "pt": "{%UPGRADED_SKILL}"
  },
  "description": {
    "fr": "{#PUSH} de {cell:Spell.119042.d1} supplémentaire.",
    "en": "{#PUSH} {cell:Spell.119042.d1} extra.",
    "es": "{#PUSH} {cell:Spell.119042.d1} más.",
    "de": "{#PUSH} zusätzlicher {cell:Spell.119042.d1}.",
    "pt": "{#PUSH} por {cell:Spell.119042.d1} adicional."
  }
}