{
  "m_GameObject": {
    "m_FileID": 0,
    "m_PathID": 0
  },
  "m_Enabled": 1,
  "m_Script": {
    "m_FileID": 0,
    "m_PathID": -6962076302617524000
  },
  "m_Name": "829",
  "m_id": 829,
  "m_displayName": "SPELL - XELOR - Sablier Cinglant 1",
  "m_availability": 3,
  "m_i18nNameId": {
    "a": 1114296277,
    "b": -241644684,
    "c": 1952979001,
    "d": 137079575,
    "e": 1013468003
  },
  "m_i18nDescriptionId": {
    "a": 1114296277,
    "b": -241644684,
    "c": 1952979001,
    "d": 137079575,
    "e": 1084724297
  },
  "m_skillIconReference": {
    "assetGuid": "a632daece8b982f4da75889d298082d7"
  },
  "values": {
    "type": "SkillDefinition",
    "id": 829,
    "skillUsageType": 0,
    "hideDescriptionInTooltip": true,
    "passiveModifiers": [],
    "nonFightSkillEffects": [],
    "precomputedData": {
      "type": "PrecomputedData",
      "dynamicValueReferences": [],
      "externalDynamicValueReferences": [
        "Spell.135380.Bper"
      ],
      "hasEffects": false,
      "keywordReferences": []
    }
  },
  "name": {
    "fr": "{%UPGRADED_SKILL}",
    "en": "{%UPGRADED_SKILL}",
    "es": "{%UPGRADED_SKILL}",
    "de": "{%UPGRADED_SKILL}",
    "pt": "{%UPGRADED_SKILL}"
  },
  "description": {
    "fr": "{value:Spell.135380.Bper,percent,+} aux <b>DÉGÂTS</b> de ce {%SPELLCOUNT,plural:one}.",
    "en": "{value:Spell.135380.Bper,percent,+} to this {%SPELLCOUNT,plural:one}'s <b>DAMAGE</b>.",
    "es": "{value:Spell.135380.Bper,percent,+} a los <b>DAÑOS</b> de este {%SPELLCOUNT,plural:one}.",
    "de": "{value:Spell.135380.Bper,percent,+} <b>SCHADEN</b> für diesen {%SPELLCOUNT,plural:one}.",
    "pt": "{value:Spell.135380.Bper,percent,+} aos <b>DANOS</b> deste {%SPELLCOUNT,plural:one}."
  }
}