{
  "m_GameObject": {
    "m_FileID": 0,
    "m_PathID": 0
  },
  "m_Enabled": 1,
  "m_Script": {
    "m_FileID": 0,
    "m_PathID": 2065592925952603065
  },
  "m_Name": "95",
  "m_id": 95,
  "m_displayName": "AMAKNA - 07 - Encerclement",
  "m_availability": 3,
  "m_wip": 0,
  "m_illustration": {
    "assetGuid": "9b1c7b0f8f31cc74db246a2743b566c0"
  },
  "m_i18nNameId": {
    "a": -731661826,
    "b": 1337866724,
    "c": 1782872424,
    "d": -1049644524,
    "e": -839990625
  },
  "m_i18nDescriptionId": {
    "a": -731661826,
    "b": 1337866724,
    "c": 1782872424,
    "d": -1049644524,
    "e": -1897741196
  },
  "m_i18nSummaryId": {
    "a": 0,
    "b": 0,
    "c": 0,
    "d": 0,
    "e": 0
  },
  "values": {
    "type": "CustomRuleDefinition",
    "id": 95,
    "precomputedData": {
      "type": "PrecomputedData",
      "dynamicValueReferences": [
        {
          "type": "LinearScaleLevelOnlyBasedDynamicValue",
          "referenceId": "dmg",
          "baseValue": 25.0,
          "factor": {
            "type": "ReferenceScalingFactor",
            "reference": 7
          }
        }
      ],
      "externalDynamicValueReferences": [],
      "hasEffects": false,
      "keywordReferences": []
    }
  },
  "name": {
    "fr": "Encerclement",
    "en": "Encirclement",
    "es": "Cerco",
    "de": "Umzingelung",
    "pt": "Cerco"
  },
  "description": {
    "fr": "{%FightTurnStartedMonsters} Si un adversaire est adjacent à aux moins <b>2 Rats</b>, il subit {magicalDamage:dmg}.",
    "en": "{%FightTurnStartedMonsters} If an opponent is adjacent to at least <b>2\\_Rats</b>,they take {magicalDamage:dmg}.",
    "es": "{%FightTurnStartedMonsters} Si un adversario está adyacente a al menos <b>2 ratas</b>, sufre {magicalDamage:dmg}.",
    "de": "{%FightTurnStartedMonsters} Grenzt ein Gegner an mindestens <b>2 Ratten</b> an, erleidet er {magicalDamage:dmg}.",
    "pt": "{%FightTurnStartedMonsters} Se um adversário estiver adjacente a <b>2 Ratos</b> ou mais, ele sofre {magicalDamage:dmg}."
  }
}