{
  "m_GameObject": {
    "m_FileID": 0,
    "m_PathID": 0
  },
  "m_Enabled": 1,
  "m_Script": {
    "m_FileID": 0,
    "m_PathID": -2964380741728395000
  },
  "m_Name": "687",
  "m_id": 687,
  "m_displayName": "DQ - MYSTERY ISLAND - VAMPYRE - 3_Arena",
  "m_availability": 3,
  "m_extendedLevelDefinition": {
    "assetGuid": "15f6fe1b186cfa44893d22b37b2e2d95"
  },
  "m_cameraControllerSettingsType": 1,
  "m_cameraRotationBehaviour": 0,
  "values": {
    "type": "MapDefinition",
    "id": 687,
    "variantId": -1,
    "gridSpawnPointGroups": [],
    "cellsFlagsMap": {
      "type": "CellsFlagsDictionary",
      "cellsFlags": []
    }
  }
}