{
  "m_GameObject": {
    "m_FileID": 0,
    "m_PathID": 0
  },
  "m_Enabled": 1,
  "m_Script": {
    "m_FileID": 0,
    "m_PathID": -200300614966713759
  },
  "m_Name": "847",
  "m_id": 847,
  "m_displayName": "DQ - CONTRAT - BOUFTOU - 2",
  "m_availability": 3,
  "m_wip": 0,
  "m_extendedLevelDefinition": {
    "assetGuid": "4cf7324fb1860d943b1e8d883508a428"
  },
  "m_cameraControllerSettingsType": 1,
  "m_cameraRotationBehaviour": 0,
  "values": {
    "type": "MapDefinition",
    "id": 847,
    "variantId": -1,
    "gridSpawnPointGroups": [],
    "cellsFlagsMap": {
      "type": "CellsFlagsDictionary",
      "cellsFlags": []
    },
    "miniMapData": null
  }
}