{
  "m_GameObject": {
    "m_FileID": 0,
    "m_PathID": 0
  },
  "m_Enabled": 1,
  "m_Script": {
    "m_FileID": 0,
    "m_PathID": 3027643183042824847
  },
  "m_Name": "239",
  "m_id": 239,
  "m_displayName": "DEFAULT SKIN - CHAFER - STATUE 3",
  "m_availability": 3,
  "m_wip": 0,
  "m_prefabReference": {
    "assetGuid": "2dbfc09b003dc1f4a8dbf98c3d393e56"
  },
  "m_previewReference": {
    "assetGuid": "f781697d96347e04c8c928ae42ec2a8e"
  },
  "m_illustrationReference": {
    "assetGuid": "58b4461bdcee0774988db55ed8e81cc4"
  },
  "m_illustrationPreviewOrthographicSize": 0.2199999988079071,
  "m_illustrationPreviewOffset": {
    "x": -0.029999999329447746,
    "y": -0.11999999731779099,
    "z": 0.0
  },
  "values": {
    "type": "HavenIslandPropSkinDefinition",
    "id": 239,
    "prefabSize": {
      "x": 0.0,
      "y": 0.0,
      "z": 0.0
    }
  }
}