{
  "m_GameObject": {
    "m_FileID": 0,
    "m_PathID": 0
  },
  "m_Enabled": 1,
  "m_Script": {
    "m_FileID": 0,
    "m_PathID": -7637285437943443000
  },
  "m_Name": "1772",
  "m_id": 1772,
  "m_displayName": "XELOR - 01364 - FEAR",
  "m_availability": 0,
  "m_wip": 1,
  "m_i18nNameId": {
    "a": 1445067065,
    "b": 915793860,
    "c": 672172042,
    "d": 34630733,
    "e": 710608088
  },
  "m_animatedObjectDefinition": {
    "assetGuid": ""
  },
  "m_smallIllustration": {
    "assetGuid": ""
  },
  "m_bigIllustration": {
    "assetGuid": ""
  },
  "m_soundGuid": "",
  "values": {
    "type": "EmoteDefinition",
    "id": 1772,
    "merchantCosts": [],
    "purchaseConditionalAvailability": {
      "type": "Available"
    },
    "emotion": 2,
    "sortInfo": null,
    "isPlayerEmote": true
  },
  "name": {
    "fr": "",
    "en": "",
    "es": "",
    "de": "",
    "pt": ""
  }
}