{
  "m_GameObject": {
    "m_FileID": 0,
    "m_PathID": 0
  },
  "m_Enabled": 1,
  "m_Script": {
    "m_FileID": 0,
    "m_PathID": -6310913346592728000
  },
  "m_Name": "178",
  "m_id": 178,
  "m_displayName": "CRA - 01250 - FEAR",
  "m_availability": 3,
  "m_wip": 0,
  "m_i18nNameId": {
    "a": -657076773,
    "b": -77338108,
    "c": 1914152104,
    "d": -272254067,
    "e": -1599676496
  },
  "m_animatedObjectDefinition": {
    "assetGuid": "e448e1538fffb4f49aa0ff4e3dcc8f74"
  },
  "m_smallIllustration": {
    "assetGuid": "be48c2578e0b8e64ba33b3b2ec2af40a"
  },
  "m_bigIllustration": {
    "assetGuid": ""
  },
  "m_soundGuid": "0de6a98891284129af6e99f953713332",
  "values": {
    "type": "EmoteDefinition",
    "id": 178,
    "merchantCosts": [],
    "purchaseConditionalAvailability": {
      "type": "Available"
    },
    "emotion": 2,
    "sortInfo": null,
    "isPlayerEmote": true
  },
  "name": {
    "fr": "",
    "en": "",
    "es": "",
    "de": "",
    "pt": ""
  }
}