{
  "m_GameObject": {
    "m_FileID": 0,
    "m_PathID": 0
  },
  "m_Enabled": 1,
  "m_Script": {
    "m_FileID": 0,
    "m_PathID": -9171159048238311428
  },
  "m_Name": "429",
  "m_id": 429,
  "m_displayName": "Season 18_Vampyre - Semaine 4 - 02_Vaincre 6 vampyres ou plus en un seul tour.",
  "m_availability": 3,
  "m_wip": 0,
  "m_i18nNameId": {
    "a": 581070160,
    "b": 1221032356,
    "c": -927014021,
    "d": 99991353,
    "e": -28273946
  },
  "values": {
    "type": "BattlePassMissionDefinition",
    "id": 429,
    "subAchievements": [
      4026
    ],
    "points": 20,
    "precomputedData": {
      "type": "PrecomputedData",
      "dynamicValueReferences": [],
      "externalDynamicValueReferences": [],
      "hasEffects": false,
      "keywordReferences": []
    }
  }
}