{
  "m_GameObject": {
    "m_FileID": 0,
    "m_PathID": 0
  },
  "m_Enabled": 1,
  "m_Script": {
    "m_FileID": 0,
    "m_PathID": -3207076657884500500
  },
  "m_Name": "337",
  "m_id": 337,
  "m_displayName": "BRACELET - COMMON - Brassard Kalibur",
  "m_availability": 3,
  "m_i18nNameId": {
    "a": 260929302,
    "b": -1245819612,
    "c": 910825640,
    "d": 115561923,
    "e": 586202579
  },
  "m_i18nDescriptionId": {
    "a": 260929302,
    "b": -1245819612,
    "c": 910825640,
    "d": 115561923,
    "e": -1039090665
  },
  "m_i18nBgDescriptionId": {
    "a": 260929302,
    "b": -1245819612,
    "c": 910825640,
    "d": 115561923,
    "e": -189337432
  },
  "m_illustration": {
    "assetGuid": "b4fb98dc19157af4a86ad60a2f49bff4"
  },
  "m_illustrationBig": {
    "assetGuid": "b4fb98dc19157af4a86ad60a2f49bff4"
  },
  "m_affinity": 0,
  "m_elementaryStates": 1,
  "values": {
    "type": "EquipmentDefinition",
    "id": 337,
    "merchantCosts": [],
    "premiumItem": false,
    "rarity": 0,
    "unlockableSkillIds": [
      655107,
      655217,
      655448,
      198,
      658733,
      659024
    ],
    "equipableByPlayers": true,
    "upgradeRuleId": 594,
    "useCharges": false,
    "precomputedData": {
      "type": "PrecomputedData",
      "dynamicValueReferences": [],
      "externalDynamicValueReferences": [],
      "hasEffects": false,
      "keywordReferences": []
    },
    "family": 0,
    "equipmentType": 2,
    "petSkins": null,
    "passiveModifiers": [
      {
        "type": "CaracBuffModifier",
        "holder": 8,
        "value": {
          "type": "LinearLevelOnlyBasedDynamicValue",
          "referenceId": "",
          "baseValue": 0,
          "factor": 1
        },
        "caracIds": [
          58
        ]
      },
      {
        "type": "CaracBuffModifier",
        "holder": 9,
        "value": {
          "type": "ConstIntegerValue",
          "referenceId": "",
          "value": 50
        },
        "caracIds": [
          71
        ]
      },
      {
        "type": "CaracBuffModifier",
        "holder": 9,
        "value": {
          "type": "ConstIntegerValue",
          "referenceId": "",
          "value": 5
        },
        "caracIds": [
          69
        ]
      }
    ],
    "spellEffectData": []
  },
  "name": {
    "fr": "Brassard Kalibur",
    "en": "Kalibur Armband",
    "es": "Brazalete Kalibur",
    "de": "Exkalibarmschiene",
    "pt": "Braçadeira Kalibur"
  },
  "description": {
    "fr": "{%empty}",
    "en": "{%empty}",
    "es": "{%empty}",
    "de": "{%empty}",
    "pt": "{%empty}"
  },
  "bgDescription": {
    "fr": "{%empty}",
    "en": "",
    "es": "",
    "de": "",
    "pt": ""
  }
}