{
  "m_GameObject": {
    "m_FileID": 0,
    "m_PathID": 0
  },
  "m_Enabled": 1,
  "m_Script": {
    "m_FileID": 0,
    "m_PathID": 4088305958716738208
  },
  "m_Name": "307",
  "m_id": 307,
  "m_displayName": "CRA - CLASSE - ETHER - Ataraxie",
  "m_availability": 3,
  "m_wip": 0,
  "m_i18nNameId": {
    "a": -554449621,
    "b": 612651572,
    "c": 1400182889,
    "d": -1543120373,
    "e": -190719654
  },
  "m_i18nDescriptionId": {
    "a": -554449621,
    "b": 612651572,
    "c": 1400182889,
    "d": -1543120373,
    "e": -955938871
  },
  "m_elementaryStates": 1,
  "m_illustrationReference": {
    "assetGuid": "c2f5ed6a5cfc2fc44a78f9d12e21041c"
  },
  "m_spellEffectOverrideReferences": {
    "m_keys": [],
    "m_values": []
  },
  "values": {
    "type": "SpellDefinition",
    "id": 307,
    "merchantCosts": [],
    "purchaseConditionalAvailability": {
      "type": "Hidden"
    },
    "rarity": 0,
    "unlockableSkillIds": [],
    "upgradeRuleId": 247,
    "canCrit": false,
    "isEphemeral": false,
    "tags": [],
    "details": {
      "type": "SpellDetails",
      "equipableByPlayers": true,
      "pvpAvailability": {
        "type": "Available"
      },
      "element": 6,
      "specificToWeapon": null,
      "families": [
        2
      ],
      "heroSkillPointsCost": 5
    },
    "gaugeToModifyOnSpellPlay": [],
    "costs": [
      {
        "type": "ActionPointsCost",
        "value": {
          "type": "ConstIntegerValue",
          "referenceId": "",
          "value": 2
        }
      }
    ],
    "castCondition": null,
    "castTarget": {
      "type": "OneCastTargetDefinition",
      "selector": {
        "type": "CasterHeroSelector"
      }
    },
    "spellEffectData": [
      {
        "type": "SpellEffectInstantiationData",
        "spellEffect": "0aaded770c78c674d84b3983577018e6",
        "originTarget": {
          "type": "FirstCastTargetSelector"
        },
        "orientation": null,
        "delay": null
      }
    ],
    "precomputedData": {
      "type": "PrecomputedData",
      "dynamicValueReferences": [
        {
          "type": "ConstIntegerValue",
          "referenceId": "d",
          "value": 2
        }
      ],
      "externalDynamicValueReferences": [],
      "hasEffects": true,
      "keywordReferences": []
    }
  },
  "name": {
    "fr": "Ataraxie",
    "en": "Ataraxia",
    "es": "Ataraxia",
    "de": "Seelenruhe",
    "pt": "Ataraxia"
  },
  "description": {
    "fr": "Piochez {SPELLCOUNTvalue:d} si aucun adversaire n'est autour\\_<sprite name=\"cell_around\"> de votre héros.",
    "en": "Draw {SPELLCOUNTvalue:d} if there are no opponents around\\_<sprite name=\"cell_around\"> your hero.",
    "es": "Sacas {SPELLCOUNTvalue:d} si no hay ningún adversario alrededor\\_<sprite name=\"cell_around\"> de tu héroe.",
    "de": "Zieht {SPELLCOUNTvalue:d}, wenn sich kein Gegner im Umkreis\\_<sprite name=\"cell_around\"> deines Helden befindet.",
    "pt": "Compre {SPELLCOUNTvalue:d} se nenhum adversário estiver em\\_volta\\_<sprite name=\"cell_around\"> do seu herói."
  }
}