{
  "m_GameObject": {
    "m_FileID": 0,
    "m_PathID": 0
  },
  "m_Enabled": 1,
  "m_Script": {
    "m_FileID": 0,
    "m_PathID": 4149792116076202553
  },
  "m_Name": "486",
  "m_id": 486,
  "m_displayName": "SEASON - FOIRE DU TROOL -  Mega-Bomba",
  "m_availability": 3,
  "m_wip": 1,
  "m_i18nNameId": {
    "a": -1546162672,
    "b": -1113851692,
    "c": 662554122,
    "d": -1136310139,
    "e": -254339534
  },
  "m_i18nDescriptionId": {
    "a": -1546162672,
    "b": -1113851692,
    "c": 662554122,
    "d": -1136310139,
    "e": -986155706
  },
  "m_elementaryStates": 1,
  "m_illustrationReference": {
    "assetGuid": "93308a255975cc34fa2fe0de239fa342"
  },
  "m_spellEffectOverrideReferences": {
    "m_keys": [],
    "m_values": []
  },
  "values": {
    "type": "SpellDefinition",
    "id": 486,
    "merchantCosts": [],
    "purchaseConditionalAvailability": {
      "type": "Hidden"
    },
    "rarity": 0,
    "unlockableSkillIds": [],
    "upgradeRuleId": null,
    "canCrit": false,
    "isEphemeral": false,
    "tags": [],
    "details": {
      "type": "SpellDetails",
      "equipableByPlayers": false,
      "pvpAvailability": {
        "type": "Available"
      },
      "element": 6,
      "specificToWeapon": null,
      "families": [],
      "heroSkillPointsCost": null
    },
    "gaugeToModifyOnSpellPlay": [],
    "costs": [
      {
        "type": "ActionPointsCost",
        "value": {
          "type": "ConstIntegerValue",
          "referenceId": "",
          "value": 0
        }
      }
    ],
    "castCondition": null,
    "castTarget": {
      "type": "OneCastTargetDefinition",
      "selector": {
        "type": "CircleAreaOfEffectSelector",
        "originSelector": {
          "type": "FilteredCoordSelector",
          "filters": [
            {
              "type": "CellValidForCharacterFilter"
            }
          ]
        },
        "size": {
          "type": "ConstIntegerValue",
          "referenceId": "",
          "value": 2
        },
        "minRadius": null
      }
    },
    "spellEffectData": [],
    "precomputedData": {
      "type": "PrecomputedData",
      "dynamicValueReferences": [],
      "externalDynamicValueReferences": [],
      "hasEffects": true,
      "keywordReferences": [
        {
          "type": 7,
          "id": 136
        }
      ]
    }
  },
  "name": {
    "fr": "Mega-Bomba"
  },
  "description": {
    "fr": "Invoque une {ObjectMechanism:136} sur une case libre du terrain."
  }
}